README.md
setup.py
nucleus_client/__init__.py
nucleus_client/api_client.py
nucleus_client/configuration.py
nucleus_client/rest.py
nucleus_client.egg-info/PKG-INFO
nucleus_client.egg-info/SOURCES.txt
nucleus_client.egg-info/dependency_links.txt
nucleus_client.egg-info/requires.txt
nucleus_client.egg-info/top_level.txt
nucleus_client/api/__init__.py
nucleus_client/api/default_api.py
nucleus_client/models/__init__.py
nucleus_client/models/activities_delete_request.py
nucleus_client/models/activity.py
nucleus_client/models/activity_keys.py
nucleus_client/models/activity_keys_item.py
nucleus_client/models/add_metric.py
nucleus_client/models/aggregation_dataset_task.py
nucleus_client/models/aggregation_parameterized_task.py
nucleus_client/models/aggregation_task.py
nucleus_client/models/aggregation_task_metric.py
nucleus_client/models/api_user.py
nucleus_client/models/array_explode_many_transform.py
nucleus_client/models/array_explode_transform.py
nucleus_client/models/array_transform.py
nucleus_client/models/base_page.py
nucleus_client/models/base_templated_page.py
nucleus_client/models/base_user.py
nucleus_client/models/batch_receipt.py
nucleus_client/models/binomial_logistic_regression_task.py
nucleus_client/models/block.py
nucleus_client/models/block_full.py
nucleus_client/models/block_type.py
nucleus_client/models/boolean_bucket_filter.py
nucleus_client/models/boolean_bucket_transform.py
nucleus_client/models/boolean_cast_transform.py
nucleus_client/models/boolean_constant_transform.py
nucleus_client/models/boolean_filter.py
nucleus_client/models/boolean_transform.py
nucleus_client/models/change_history.py
nucleus_client/models/client.py
nucleus_client/models/client_default_user.py
nucleus_client/models/client_features.py
nucleus_client/models/client_package.py
nucleus_client/models/client_package_status.py
nucleus_client/models/client_settings.py
nucleus_client/models/client_settings_update.py
nucleus_client/models/client_sso.py
nucleus_client/models/client_sso_browser_policy.py
nucleus_client/models/client_update.py
nucleus_client/models/coalesce_transform.py
nucleus_client/models/collection_size_transform.py
nucleus_client/models/column_mapping.py
