Metadata-Version: 2.1
Name: nucleus_client
Version: 0.17.7
Summary: Nucleus API
Home-page: 
Author-email: 
Keywords: OpenAPI,OpenAPI-Generator,Nucleus API
Requires-Dist: urllib3>=1.15
Requires-Dist: six>=1.10
Requires-Dist: certifi
Requires-Dist: python-dateutil
